<?xml version="1.0" encoding="utf-8" ?>
<dwsync>
<file name="elfinder.ar.js" server="178.210.67.85/insur.nichost.ru/docs/" local="129994615572878000" remote="129994666200000000" />
<file name="elfinder.bg.js" server="178.210.67.85/insur.nichost.ru/docs/" local="129994615572928000" remote="129994666200000000" />
<file name="elfinder.ca.js" server="178.210.67.85/insur.nichost.ru/docs/" local="129994615572948000" remote="129994666200000000" />
<file name="elfinder.cs.js" server="178.210.67.85/insur.nichost.ru/docs/" local="129994615572968000" remote="129994666200000000" />
<file name="elfinder.de.js" server="178.210.67.85/insur.nichost.ru/docs/" local="129994615572998000" remote="129994666200000000" />
<file name="elfinder.es.js" server="178.210.67.85/insur.nichost.ru/docs/" local="129994615573028000" remote="129994666200000000" />
<file name="elfinder.fr.js" server="178.210.67.85/insur.nichost.ru/docs/" local="129994615573728000" remote="129994666200000000" />
<file name="elfinder.hu.js" server="178.210.67.85/insur.nichost.ru/docs/" local="129994615573748000" remote="129994666200000000" />
<file name="elfinder.jp.js" server="178.210.67.85/insur.nichost.ru/docs/" local="129994615573778000" remote="129994666200000000" />
<file name="elfinder.LANG.js" server="178.210.67.85/insur.nichost.ru/docs/" local="129994615572858000" remote="129994666200000000" />
<file name="elfinder.nl.js" server="178.210.67.85/insur.nichost.ru/docs/" local="129994615573808000" remote="129994666200000000" />
<file name="elfinder.no.js" server="178.210.67.85/insur.nichost.ru/docs/" local="129994615573828000" remote="129994666200000000" />
<file name="elfinder.pl.js" server="178.210.67.85/insur.nichost.ru/docs/" local="129994615573938000" remote="129994666200000000" />
<file name="elfinder.pt_BR.js" server="178.210.67.85/insur.nichost.ru/docs/" local="129994615573968000" remote="129994666800000000" />
<file name="elfinder.ru.js" server="178.210.67.85/insur.nichost.ru/docs/" local="129994615574068000" remote="129994666800000000" />
<file name="elfinder.zh_CN.js" server="178.210.67.85/insur.nichost.ru/docs/" local="129994615574088000" remote="129994666800000000" />
</dwsync>