<?xml version="1.0" encoding="utf-8" ?>
<dwsync>
<file name="bootstrap.less" server="178.210.67.85/insur.nichost.ru/docs/" local="129999706374370000" remote="129999711600000000" />
<file name="forms.less" server="178.210.67.85/insur.nichost.ru/docs/" local="129999706374370000" remote="129999711600000000" />
<file name="mixins.less" server="178.210.67.85/insur.nichost.ru/docs/" local="129999706374380000" remote="129999711600000000" />
<file name="patterns.less" server="178.210.67.85/insur.nichost.ru/docs/" local="129999706374410000" remote="129999711600000000" />
<file name="reset.less" server="178.210.67.85/insur.nichost.ru/docs/" local="129999706374420000" remote="129999711600000000" />
<file name="scaffolding.less" server="178.210.67.85/insur.nichost.ru/docs/" local="129999706374430000" remote="129999711600000000" />
<file name="tables.less" server="178.210.67.85/insur.nichost.ru/docs/" local="129999706374440000" remote="129999711600000000" />
<file name="type.less" server="178.210.67.85/insur.nichost.ru/docs/" local="129999706374450000" remote="129999711600000000" />
<file name="variables.less" server="178.210.67.85/insur.nichost.ru/docs/" local="129999706374460000" remote="129999711600000000" />
</dwsync>