<?xml version="1.0" encoding="utf-8" ?>
<dwsync>
<file name="bootstrap-box.css" server="178.210.67.85/insur.nichost.ru/docs/" local="130000658854390000" remote="130000663800000000" />
<file name="bootstrap-colorpicker.css" server="178.210.67.85/insur.nichost.ru/docs/" local="130000658854420000" remote="130000663800000000" />
<file name="bootstrap-datepicker.css" server="178.210.67.85/insur.nichost.ru/docs/" local="130000658854440000" remote="130000663800000000" />
<file name="bootstrap-daterangepicker.css" server="178.210.67.85/insur.nichost.ru/docs/" local="130000658854460000" remote="130000663800000000" />
<file name="bootstrap-editable-tooltip.css" server="178.210.67.85/insur.nichost.ru/docs/" local="130000658855000000" remote="130000663800000000" />
<file name="bootstrap-editable.css" server="178.210.67.85/insur.nichost.ru/docs/" local="130000658855030000" remote="130000663800000000" />
<file name="bootstrap-picker.css" server="178.210.67.85/insur.nichost.ru/docs/" local="130000658855040000" remote="130000663800000000" />
<file name="bootstrap-relational.css" server="178.210.67.85/insur.nichost.ru/docs/" local="130000658855050000" remote="130000663800000000" />
<file name="bootstrap-responsive.css" server="178.210.67.85/insur.nichost.ru/docs/" local="130000658855160000" remote="130000663800000000" />
<file name="bootstrap-responsive.min.css" server="178.210.67.85/insur.nichost.ru/docs/" local="130000658855200000" remote="130000663800000000" />
<file name="bootstrap-timepicker.css" server="178.210.67.85/insur.nichost.ru/docs/" local="130000658855210000" remote="130000663800000000" />
<file name="bootstrap-toggle-buttons.css" server="178.210.67.85/insur.nichost.ru/docs/" local="130000658855230000" remote="130000663800000000" />
<file name="bootstrap-wysihtml5.css" server="178.210.67.85/insur.nichost.ru/docs/" local="130000658855250000" remote="130000663800000000" />
<file name="bootstrap-yii.css" server="178.210.67.85/insur.nichost.ru/docs/" local="130000658855270000" remote="130000663800000000" />
<file name="bootstrap.css" server="178.210.67.85/insur.nichost.ru/docs/" local="130000658855390000" remote="130000664400000000" />
<file name="bootstrap.min.css" server="178.210.67.85/insur.nichost.ru/docs/" local="130000658855510000" remote="130000664400000000" />
<file name="easy-pie-chart.css" server="178.210.67.85/insur.nichost.ru/docs/" local="130000658855520000" remote="130000664400000000" />
<file name="jquery-ui-bootstrap.css" server="178.210.67.85/insur.nichost.ru/docs/" local="130000658855680000" remote="130000664400000000" />
<file name="redactor.css" server="178.210.67.85/insur.nichost.ru/docs/" local="130000658855740000" remote="130000664400000000" />
<file name="wysiwyg-color.css" server="178.210.67.85/insur.nichost.ru/docs/" local="130000658855760000" remote="130000664400000000" />
</dwsync>